{
    "Group F": [
        {
            "Pos": 1,
            "Team": "SwedenSWEGroup F",
            "Code": "",
            "Played": 3,
            "Won": 1,
            "Drawn": 1,
            "Lost": 1,
            "GF": 7,
            "GA": 7,
            "GD": 0,
            "Points": 4
        },
        {
            "Pos": 2,
            "Team": "EcuadorECUGroup E",
            "Code": "",
            "Played": 3,
            "Won": 1,
            "Drawn": 1,
            "Lost": 1,
            "GF": 2,
            "GA": 2,
            "GD": 0,
            "Points": 4
        },
        {
            "Pos": 3,
            "Team": "Bosnia and HerzegovinaBIHGroup B",
            "Code": "",
            "Played": 3,
            "Won": 1,
            "Drawn": 1,
            "Lost": 1,
            "GF": 5,
            "GA": 6,
            "GD": -1,
            "Points": 4
        },
        {
            "Pos": 4,
            "Team": "ParaguayPARGroup D",
            "Code": "",
            "Played": 3,
            "Won": 1,
            "Drawn": 1,
            "Lost": 1,
            "GF": 2,
            "GA": 4,
            "GD": -2,
            "Points": 4
        },
        {
            "Pos": 5,
            "Team": "SenegalSENGroup I",
            "Code": "",
            "Played": 3,
            "Won": 1,
            "Drawn": 0,
            "Lost": 2,
            "GF": 8,
            "GA": 6,
            "GD": 2,
            "Points": 3
        },
        {
            "Pos": 6,
            "Team": "IR IranIRNGroup G",
            "Code": "",
            "Played": 3,
            "Won": 0,
            "Drawn": 3,
            "Lost": 0,
            "GF": 3,
            "GA": 3,
            "GD": 0,
            "Points": 3
        },
        {
            "Pos": 7,
            "Team": "CroatiaCROGroup L",
            "Code": "",
            "Played": 2,
            "Won": 1,
            "Drawn": 0,
            "Lost": 1,
            "GF": 3,
            "GA": 4,
            "GD": -1,
            "Points": 3
        },
        {
            "Pos": 8,
            "Team": "Korea RepublicKORGroup A",
            "Code": "",
            "Played": 3,
            "Won": 1,
            "Drawn": 0,
            "Lost": 2,
            "GF": 2,
            "GA": 3,
            "GD": -1,
            "Points": 3
        },
        {
            "Pos": 9,
            "Team": "AlgeriaALGGroup J",
            "Code": "",
            "Played": 2,
            "Won": 1,
            "Drawn": 0,
            "Lost": 1,
            "GF": 2,
            "GA": 4,
            "GD": -2,
            "Points": 3
        },
        {
            "Pos": 10,
            "Team": "ScotlandSCOGroup C",
            "Code": "",
            "Played": 3,
            "Won": 1,
            "Drawn": 0,
            "Lost": 2,
            "GF": 1,
            "GA": 4,
            "GD": -3,
            "Points": 3
        },
        {
            "Pos": 11,
            "Team": "UruguayURUGroup H",
            "Code": "",
            "Played": 3,
            "Won": 0,
            "Drawn": 2,
            "Lost": 1,
            "GF": 3,
            "GA": 4,
            "GD": -1,
            "Points": 2
        },
        {
            "Pos": 12,
            "Team": "Congo DRCODGroup K",
            "Code": "",
            "Played": 2,
            "Won": 0,
            "Drawn": 1,
            "Lost": 1,
            "GF": 1,
            "GA": 2,
            "GD": -1,
            "Points": 1
        }
    ]
}